<?xml version="1.0" encoding="utf-8"?>
<!--DO NOT EDIT. This document is generated by PSoC Creator design builds.-->
<PSoCCreatorIdeExport Version="1">
  <Device Part="CY8C4045AZI-S413" Processor="CortexM0p" DeviceID="190111A9" />
  <Toolchains>
    <Toolchain Name="ARM GCC Generic" Selected="True">
      <Tool Name="prebuild" Command="" Options="" />
      <Tool Name="assembler" Command="arm-none-eabi-as.exe" Options="-mcpu=cortex-m0plus -mthumb -I. -IGenerated_Source\PSoC4 -alh=${OutputDir}/${CompileFile}.lst -g -W" />
      <Tool Name="compiler" Command="arm-none-eabi-gcc.exe" Options="-mcpu=cortex-m0plus -mthumb -I. -IGenerated_Source\PSoC4 -Wa,-alh=${OutputDir}/${CompileFile}.lst -g -D DEBUG -D CY_CORE_ID=0 -Wall -ffunction-sections -ffat-lto-objects -Og" />
      <Tool Name="linker" Command="arm-none-eabi-gcc.exe" Options="-mcpu=cortex-m0plus -mthumb -L Generated_Source\PSoC4 -Wl,-Map,${OutputDir}/${ProjectShortName}.map -T Generated_Source\PSoC4\cm0plusgcc.ld -specs=nano.specs -Wl,--gc-sections -g -ffunction-sections -Og -ffat-lto-objects" />
      <Tool Name="postbuild" Command="" Options="" />
    </Toolchain>
    <Toolchain Name="ARM MDK Generic" Selected="False">
      <Tool Name="prebuild" Command="" Options="" />
      <Tool Name="assembler" Command="armasm.exe" Options="--cpu=Cortex-M0plus --diag_style=gnu --thumb -i. -iGenerated_Source\PSoC4 -g --list=${OutputDir}/${CompileFile}.lst &quot;--predefine=__MICROLIB SETA 1&quot;" />
      <Tool Name="compiler" Command="armcc.exe" Options="--cpu=Cortex-M0plus --C99 --diag_style=gnu -I. -IGenerated_Source\PSoC4 --list --signed_chars -g -D DEBUG -D CY_CORE_ID=0 -O0 --split_sections -D__MICROLIB" />
      <Tool Name="linker" Command="armlink.exe" Options="--cpu=Cortex-M0plus --diag_style=gnu --no_startup --library_type=microlib --map --list ${OutputDir}/${ProjectShortName}.map --scatter Generated_Source\PSoC4\Cm0plusRealView.scat" />
      <Tool Name="postbuild" Command="" Options="" />
    </Toolchain>
    <Toolchain Name="ARM IAR Generic" Selected="False">
      <Tool Name="prebuild" Command="" Options="" />
      <Tool Name="assembler" Command="iasmarm.exe" Options="--cpu Cortex-M0+ -I. -IGenerated_Source\PSoC4 -s+ -M&lt;&gt; -w+ -r -DDEBUG --fpu None" />
      <Tool Name="compiler" Command="iccarm.exe" Options="--cpu Cortex-M0+ -I. -IGenerated_Source\PSoC4 -D DEBUG -D CY_CORE_ID=0 -I. -IGenerated_Source\PSoC4 -D DEBUG -D CY_CORE_ID=0 --no_cse --no_unroll --no_inline --no_code_motion --no_tbaa --no_clustering --no_scheduling --debug --endian=little -e --fpu=None -On --no_wrap_diagnostics" />
      <Tool Name="linker" Command="ilinkarm.exe" Options="--semihosting --entry __iar_program_start --config Generated_Source\PSoC4\Cm0plusIar.icf" />
      <Tool Name="postbuild" Command="" Options="" />
    </Toolchain>
  </Toolchains>
  <Project Name="Configuracion_General" Path="D:\Documentos\UD\2023-3\Proyecto de grado\Ejemplos\Configuracion General\Configuracion_General\Configuracion_General.cydsn" Version="6.10" Type="Normal">
    <CMSIS_SVD_File>Configuracion_General.svd</CMSIS_SVD_File>
    <Datasheet>Configuracion_General_datasheet.pdf</Datasheet>
    <LinkerFiles>
      <LinkerFile Toolchain="ARM GCC Generic">.\Generated_Source\PSoC4\cm0plusgcc.ld</LinkerFile>
      <LinkerFile Toolchain="ARM MDK Generic">.\Generated_Source\PSoC4\Cm0plusRealView.scat</LinkerFile>
      <LinkerFile Toolchain="ARM IAR Generic">.\Generated_Source\PSoC4\Cm0plusIar.icf</LinkerFile>
    </LinkerFiles>
    <Folders>
      <Folder BuildType="STRICT" Path="D:\Documentos\UD\2023-3\Proyecto de grado\Ejemplos\Configuracion General\Configuracion_General\Configuracion_General.cydsn">
        <Files Root="D:\Documentos\UD\2023-3\Proyecto de grado\Ejemplos\Configuracion General\Configuracion_General\Configuracion_General.cydsn">
          <File BuildType="BUILD" Toolchain="">main.c</File>
          <File BuildType="BUILD" Toolchain="">cyapicallbacks.h</File>
        </Files>
      </Folder>
      <Folder BuildType="STRICT" Path="D:\Documentos\UD\2023-3\Proyecto de grado\Ejemplos\Configuracion General\Configuracion_General\Configuracion_General.cydsn\Generated_Source\PSoC4">
        <Files Root="D:\Documentos\UD\2023-3\Proyecto de grado\Ejemplos\Configuracion General\Configuracion_General\Configuracion_General.cydsn">
          <File BuildType="BUILD" Toolchain="">Generated_Source\PSoC4\cyfitter_cfg.h</File>
          <File BuildType="BUILD" Toolchain="">Generated_Source\PSoC4\cyfitter_cfg.c</File>
          <File BuildType="BUILD" Toolchain="">Generated_Source\PSoC4\cymetadata.c</File>
          <File BuildType="BUILD" Toolchain="">Generated_Source\PSoC4\cydevice_trm.h</File>
          <File BuildType="BUILD" Toolchain="">Generated_Source\PSoC4\cydevicegnu_trm.inc</File>
          <File BuildType="BUILD" Toolchain="">Generated_Source\PSoC4\cydevicerv_trm.inc</File>
          <File BuildType="BUILD" Toolchain="">Generated_Source\PSoC4\cydeviceiar_trm.inc</File>
          <File BuildType="BUILD" Toolchain="">Generated_Source\PSoC4\cyfittergnu.inc</File>
          <File BuildType="BUILD" Toolchain="">Generated_Source\PSoC4\cyfitterrv.inc</File>
          <File BuildType="BUILD" Toolchain="">Generated_Source\PSoC4\cyfitteriar.inc</File>
          <File BuildType="BUILD" Toolchain="">Generated_Source\PSoC4\cyfitter.h</File>
          <File BuildType="BUILD" Toolchain="">Generated_Source\PSoC4\cydisabledsheets.h</File>
          <File BuildType="BUILD" Toolchain="">Generated_Source\PSoC4\UART.c</File>
          <File BuildType="BUILD" Toolchain="">Generated_Source\PSoC4\UART.h</File>
          <File BuildType="BUILD" Toolchain="">Generated_Source\PSoC4\UART_SPI_UART.h</File>
          <File BuildType="BUILD" Toolchain="">Generated_Source\PSoC4\UART_SPI_UART.c</File>
          <File BuildType="BUILD" Toolchain="">Generated_Source\PSoC4\UART_SPI_UART_INT.c</File>
          <File BuildType="BUILD" Toolchain="">Generated_Source\PSoC4\UART_PM.c</File>
          <File BuildType="BUILD" Toolchain="">Generated_Source\PSoC4\UART_UART.c</File>
          <File BuildType="BUILD" Toolchain="">Generated_Source\PSoC4\UART_BOOT.c</File>
          <File BuildType="BUILD" Toolchain="">Generated_Source\PSoC4\UART_UART_BOOT.c</File>
          <File BuildType="BUILD" Toolchain="">Generated_Source\PSoC4\UART_PINS.h</File>
          <File BuildType="BUILD" Toolchain="">Generated_Source\PSoC4\UART_SPI_UART_PVT.h</File>
          <File BuildType="BUILD" Toolchain="">Generated_Source\PSoC4\UART_PVT.h</File>
          <File BuildType="BUILD" Toolchain="">Generated_Source\PSoC4\UART_BOOT.h</File>
          <File BuildType="BUILD" Toolchain="">Generated_Source\PSoC4\UART_SCBCLK.c</File>
          <File BuildType="BUILD" Toolchain="">Generated_Source\PSoC4\UART_SCBCLK.h</File>
          <File BuildType="BUILD" Toolchain="">Generated_Source\PSoC4\UART_tx.c</File>
          <File BuildType="BUILD" Toolchain="">Generated_Source\PSoC4\UART_tx.h</File>
          <File BuildType="BUILD" Toolchain="">Generated_Source\PSoC4\UART_tx_aliases.h</File>
          <File BuildType="BUILD" Toolchain="">Generated_Source\PSoC4\UART_tx_PM.c</File>
          <File BuildType="BUILD" Toolchain="">Generated_Source\PSoC4\UART_rx.c</File>
          <File BuildType="BUILD" Toolchain="">Generated_Source\PSoC4\UART_rx.h</File>
          <File BuildType="BUILD" Toolchain="">Generated_Source\PSoC4\UART_rx_aliases.h</File>
          <File BuildType="BUILD" Toolchain="">Generated_Source\PSoC4\UART_rx_PM.c</File>
          <File BuildType="BUILD" Toolchain="ARM GCC Generic">Generated_Source\PSoC4\cm0plusgcc.ld</File>
          <File BuildType="BUILD" Toolchain="ARM MDK Generic">Generated_Source\PSoC4\Cm0plusRealView.scat</File>
          <File BuildType="BUILD" Toolchain="">Generated_Source\PSoC4\Cm0plusStart.c</File>
          <File BuildType="BUILD" Toolchain="ARM MDK Generic">Generated_Source\PSoC4\CyBootAsmRv.s</File>
          <File BuildType="BUILD" Toolchain="">Generated_Source\PSoC4\CyFlash.c</File>
          <File BuildType="BUILD" Toolchain="">Generated_Source\PSoC4\CyFlash.h</File>
          <File BuildType="BUILD" Toolchain="">Generated_Source\PSoC4\CyLib.c</File>
          <File BuildType="BUILD" Toolchain="">Generated_Source\PSoC4\CyLib.h</File>
          <File BuildType="BUILD" Toolchain="">Generated_Source\PSoC4\cyPm.c</File>
          <File BuildType="BUILD" Toolchain="">Generated_Source\PSoC4\cyPm.h</File>
          <File BuildType="BUILD" Toolchain="">Generated_Source\PSoC4\cytypes.h</File>
          <File BuildType="BUILD" Toolchain="">Generated_Source\PSoC4\cyutils.c</File>
          <File BuildType="BUILD" Toolchain="">Generated_Source\PSoC4\cypins.h</File>
          <File BuildType="BUILD" Toolchain="">Generated_Source\PSoC4\core_cmFunc.h</File>
          <File BuildType="BUILD" Toolchain="">Generated_Source\PSoC4\core_cmInstr.h</File>
          <File BuildType="BUILD" Toolchain="ARM IAR Generic">Generated_Source\PSoC4\Cm0plusIar.icf</File>
          <File BuildType="BUILD" Toolchain="ARM IAR Generic">Generated_Source\PSoC4\CyBootAsmIar.s</File>
          <File BuildType="BUILD" Toolchain="">Generated_Source\PSoC4\cmsis_armcc.h</File>
          <File BuildType="BUILD" Toolchain="">Generated_Source\PSoC4\cmsis_gcc.h</File>
          <File BuildType="BUILD" Toolchain="">Generated_Source\PSoC4\core_cm0plus.h</File>
          <File BuildType="BUILD" Toolchain="">Generated_Source\PSoC4\core_cm0plus_psoc4.h</File>
          <File BuildType="BUILD" Toolchain="">Generated_Source\PSoC4\cmsis_compiler.h</File>
          <File BuildType="BUILD" Toolchain="ARM GCC Generic">Generated_Source\PSoC4\CyBootAsmGnu.s</File>
          <File BuildType="BUILD" Toolchain="">Generated_Source\PSoC4\CyLFClk.c</File>
          <File BuildType="BUILD" Toolchain="">Generated_Source\PSoC4\CyLFClk.h</File>
          <File BuildType="BUILD" Toolchain="">Generated_Source\PSoC4\cy_em_eeprom.c</File>
          <File BuildType="BUILD" Toolchain="">Generated_Source\PSoC4\cy_em_eeprom.h</File>
          <File BuildType="BUILD" Toolchain="">Generated_Source\PSoC4\project.h</File>
          <File BuildType="BUILD" Toolchain="">Generated_Source\PSoC4\cycodeshareimport.ld</File>
          <File BuildType="BUILD" Toolchain="">Generated_Source\PSoC4\cycodeshareexport.ld</File>
          <File BuildType="BUILD" Toolchain="">Generated_Source\PSoC4\cycodeshareimport.scat</File>
          <File BuildType="BUILD" Toolchain="">Generated_Source\PSoC4\PWM1.c</File>
          <File BuildType="BUILD" Toolchain="">Generated_Source\PSoC4\PWM1.h</File>
          <File BuildType="BUILD" Toolchain="">Generated_Source\PSoC4\PWM1_PM.c</File>
          <File BuildType="BUILD" Toolchain="">Generated_Source\PSoC4\Clock1.c</File>
          <File BuildType="BUILD" Toolchain="">Generated_Source\PSoC4\Clock1.h</File>
          <File BuildType="BUILD" Toolchain="">Generated_Source\PSoC4\Out_PWM1.c</File>
          <File BuildType="BUILD" Toolchain="">Generated_Source\PSoC4\Out_PWM1.h</File>
          <File BuildType="BUILD" Toolchain="">Generated_Source\PSoC4\Out_PWM1_aliases.h</File>
          <File BuildType="BUILD" Toolchain="">Generated_Source\PSoC4\Out_PWM1_PM.c</File>
          <File BuildType="BUILD" Toolchain="">Generated_Source\PSoC4\PWM2.c</File>
          <File BuildType="BUILD" Toolchain="">Generated_Source\PSoC4\PWM2.h</File>
          <File BuildType="BUILD" Toolchain="">Generated_Source\PSoC4\PWM2_PM.c</File>
          <File BuildType="BUILD" Toolchain="">Generated_Source\PSoC4\Clock2.c</File>
          <File BuildType="BUILD" Toolchain="">Generated_Source\PSoC4\Clock2.h</File>
          <File BuildType="BUILD" Toolchain="">Generated_Source\PSoC4\Out_PWM2.c</File>
          <File BuildType="BUILD" Toolchain="">Generated_Source\PSoC4\Out_PWM2.h</File>
          <File BuildType="BUILD" Toolchain="">Generated_Source\PSoC4\Out_PWM2_aliases.h</File>
          <File BuildType="BUILD" Toolchain="">Generated_Source\PSoC4\Out_PWM2_PM.c</File>
          <File BuildType="BUILD" Toolchain="">Generated_Source\PSoC4\Clock3.c</File>
          <File BuildType="BUILD" Toolchain="">Generated_Source\PSoC4\Clock3.h</File>
          <File BuildType="BUILD" Toolchain="">Generated_Source\PSoC4\PWM3.c</File>
          <File BuildType="BUILD" Toolchain="">Generated_Source\PSoC4\PWM3.h</File>
          <File BuildType="BUILD" Toolchain="">Generated_Source\PSoC4\PWM3_PM.c</File>
          <File BuildType="BUILD" Toolchain="">Generated_Source\PSoC4\Out_PWM3.c</File>
          <File BuildType="BUILD" Toolchain="">Generated_Source\PSoC4\Out_PWM3.h</File>
          <File BuildType="BUILD" Toolchain="">Generated_Source\PSoC4\Out_PWM3_aliases.h</File>
          <File BuildType="BUILD" Toolchain="">Generated_Source\PSoC4\Out_PWM3_PM.c</File>
          <File BuildType="BUILD" Toolchain="">Generated_Source\PSoC4\CapSense.h</File>
          <File BuildType="BUILD" Toolchain="">Generated_Source\PSoC4\CapSense_Control.c</File>
          <File BuildType="BUILD" Toolchain="">Generated_Source\PSoC4\CapSense_Processing.c</File>
          <File BuildType="BUILD" Toolchain="">Generated_Source\PSoC4\CapSense_Structure.c</File>
          <File BuildType="BUILD" Toolchain="">Generated_Source\PSoC4\CapSense_Tuner.c</File>
          <File BuildType="BUILD" Toolchain="">Generated_Source\PSoC4\CapSense_Filter.c</File>
          <File BuildType="BUILD" Toolchain="">Generated_Source\PSoC4\CapSense_Sensing.c</File>
          <File BuildType="BUILD" Toolchain="">Generated_Source\PSoC4\CapSense_Control.h</File>
          <File BuildType="BUILD" Toolchain="">Generated_Source\PSoC4\CapSense_Filter.h</File>
          <File BuildType="BUILD" Toolchain="">Generated_Source\PSoC4\CapSense_Processing.h</File>
          <File BuildType="BUILD" Toolchain="">Generated_Source\PSoC4\CapSense_Sensing.h</File>
          <File BuildType="BUILD" Toolchain="">Generated_Source\PSoC4\CapSense_Structure.h</File>
          <File BuildType="BUILD" Toolchain="">Generated_Source\PSoC4\CapSense_Tuner.h</File>
          <File BuildType="BUILD" Toolchain="">Generated_Source\PSoC4\CapSense_Configuration.h</File>
          <File BuildType="BUILD" Toolchain="">Generated_Source\PSoC4\CapSense_INT.c</File>
          <File BuildType="BUILD" Toolchain="">Generated_Source\PSoC4\CapSense_SensingCSD_LL.c</File>
          <File BuildType="BUILD" Toolchain="">Generated_Source\PSoC4\CapSense_SensingCSD_LL.h</File>
          <File BuildType="BUILD" Toolchain="">Generated_Source\PSoC4\CapSense_SensingCSX_LL.h</File>
          <File BuildType="BUILD" Toolchain="">Generated_Source\PSoC4\CapSense_SensingCSX_LL.c</File>
          <File BuildType="BUILD" Toolchain="">Generated_Source\PSoC4\CapSense_RegisterMap.h</File>
          <File BuildType="BUILD" Toolchain="">Generated_Source\PSoC4\CapSense_Centroid_LL.c</File>
          <File BuildType="BUILD" Toolchain="">Generated_Source\PSoC4\CapSense_Centroid_LL.h</File>
          <File BuildType="BUILD" Toolchain="">Generated_Source\PSoC4\CapSense_ISR.c</File>
          <File BuildType="BUILD" Toolchain="">Generated_Source\PSoC4\CapSense_ISR.h</File>
          <File BuildType="BUILD" Toolchain="">Generated_Source\PSoC4\LED5.c</File>
          <File BuildType="BUILD" Toolchain="">Generated_Source\PSoC4\LED5.h</File>
          <File BuildType="BUILD" Toolchain="">Generated_Source\PSoC4\LED5_aliases.h</File>
          <File BuildType="BUILD" Toolchain="">Generated_Source\PSoC4\LED5_PM.c</File>
          <File BuildType="BUILD" Toolchain="">Generated_Source\PSoC4\LED4.c</File>
          <File BuildType="BUILD" Toolchain="">Generated_Source\PSoC4\LED4.h</File>
          <File BuildType="BUILD" Toolchain="">Generated_Source\PSoC4\LED4_aliases.h</File>
          <File BuildType="BUILD" Toolchain="">Generated_Source\PSoC4\LED4_PM.c</File>
          <File BuildType="BUILD" Toolchain="">Generated_Source\PSoC4\LED6.c</File>
          <File BuildType="BUILD" Toolchain="">Generated_Source\PSoC4\LED6.h</File>
          <File BuildType="BUILD" Toolchain="">Generated_Source\PSoC4\LED6_aliases.h</File>
          <File BuildType="BUILD" Toolchain="">Generated_Source\PSoC4\LED6_PM.c</File>
          <File BuildType="BUILD" Toolchain="">Generated_Source\PSoC4\LED7.c</File>
          <File BuildType="BUILD" Toolchain="">Generated_Source\PSoC4\LED7.h</File>
          <File BuildType="BUILD" Toolchain="">Generated_Source\PSoC4\LED7_aliases.h</File>
          <File BuildType="BUILD" Toolchain="">Generated_Source\PSoC4\LED7_PM.c</File>
          <File BuildType="BUILD" Toolchain="">Generated_Source\PSoC4\LED8.c</File>
          <File BuildType="BUILD" Toolchain="">Generated_Source\PSoC4\LED8.h</File>
          <File BuildType="BUILD" Toolchain="">Generated_Source\PSoC4\LED8_aliases.h</File>
          <File BuildType="BUILD" Toolchain="">Generated_Source\PSoC4\LED8_PM.c</File>
          <File BuildType="BUILD" Toolchain="">Generated_Source\PSoC4\LED9.c</File>
          <File BuildType="BUILD" Toolchain="">Generated_Source\PSoC4\LED9.h</File>
          <File BuildType="BUILD" Toolchain="">Generated_Source\PSoC4\LED9_aliases.h</File>
          <File BuildType="BUILD" Toolchain="">Generated_Source\PSoC4\LED9_PM.c</File>
          <File BuildType="BUILD" Toolchain="">Generated_Source\PSoC4\LED10.c</File>
          <File BuildType="BUILD" Toolchain="">Generated_Source\PSoC4\LED10.h</File>
          <File BuildType="BUILD" Toolchain="">Generated_Source\PSoC4\LED10_aliases.h</File>
          <File BuildType="BUILD" Toolchain="">Generated_Source\PSoC4\LED10_PM.c</File>
          <File BuildType="BUILD" Toolchain="">Generated_Source\PSoC4\LED11.c</File>
          <File BuildType="BUILD" Toolchain="">Generated_Source\PSoC4\LED11.h</File>
          <File BuildType="BUILD" Toolchain="">Generated_Source\PSoC4\LED11_aliases.h</File>
          <File BuildType="BUILD" Toolchain="">Generated_Source\PSoC4\LED11_PM.c</File>
          <File BuildType="BUILD" Toolchain="">Generated_Source\PSoC4\SW2.c</File>
          <File BuildType="BUILD" Toolchain="">Generated_Source\PSoC4\SW2.h</File>
          <File BuildType="BUILD" Toolchain="">Generated_Source\PSoC4\SW2_aliases.h</File>
          <File BuildType="BUILD" Toolchain="">Generated_Source\PSoC4\SW2_PM.c</File>
          <File BuildType="BUILD" Toolchain="">Generated_Source\PSoC4\LED1.c</File>
          <File BuildType="BUILD" Toolchain="">Generated_Source\PSoC4\LED1.h</File>
          <File BuildType="BUILD" Toolchain="">Generated_Source\PSoC4\LED1_aliases.h</File>
          <File BuildType="BUILD" Toolchain="">Generated_Source\PSoC4\LED1_PM.c</File>
          <File BuildType="BUILD" Toolchain="">Generated_Source\PSoC4\DI1.c</File>
          <File BuildType="BUILD" Toolchain="">Generated_Source\PSoC4\DI1.h</File>
          <File BuildType="BUILD" Toolchain="">Generated_Source\PSoC4\DI1_aliases.h</File>
          <File BuildType="BUILD" Toolchain="">Generated_Source\PSoC4\DI1_PM.c</File>
          <File BuildType="BUILD" Toolchain="">Generated_Source\PSoC4\DO1.c</File>
          <File BuildType="BUILD" Toolchain="">Generated_Source\PSoC4\DO1.h</File>
          <File BuildType="BUILD" Toolchain="">Generated_Source\PSoC4\DO1_aliases.h</File>
          <File BuildType="BUILD" Toolchain="">Generated_Source\PSoC4\DO1_PM.c</File>
          <File BuildType="BUILD" Toolchain="">Generated_Source\PSoC4\DI2.c</File>
          <File BuildType="BUILD" Toolchain="">Generated_Source\PSoC4\DI2.h</File>
          <File BuildType="BUILD" Toolchain="">Generated_Source\PSoC4\DI2_aliases.h</File>
          <File BuildType="BUILD" Toolchain="">Generated_Source\PSoC4\DI2_PM.c</File>
          <File BuildType="BUILD" Toolchain="">Generated_Source\PSoC4\DO2.c</File>
          <File BuildType="BUILD" Toolchain="">Generated_Source\PSoC4\DO2.h</File>
          <File BuildType="BUILD" Toolchain="">Generated_Source\PSoC4\DO2_aliases.h</File>
          <File BuildType="BUILD" Toolchain="">Generated_Source\PSoC4\DO2_PM.c</File>
          <File BuildType="BUILD" Toolchain="">Generated_Source\PSoC4\DI3.c</File>
          <File BuildType="BUILD" Toolchain="">Generated_Source\PSoC4\DI3.h</File>
          <File BuildType="BUILD" Toolchain="">Generated_Source\PSoC4\DI3_aliases.h</File>
          <File BuildType="BUILD" Toolchain="">Generated_Source\PSoC4\DI3_PM.c</File>
          <File BuildType="BUILD" Toolchain="">Generated_Source\PSoC4\DO3.c</File>
          <File BuildType="BUILD" Toolchain="">Generated_Source\PSoC4\DO3.h</File>
          <File BuildType="BUILD" Toolchain="">Generated_Source\PSoC4\DO3_aliases.h</File>
          <File BuildType="BUILD" Toolchain="">Generated_Source\PSoC4\DO3_PM.c</File>
        </Files>
      </Folder>
      <Folder BuildType="STRICT" Path="D:\Documentos\UD\2023-3\Proyecto de grado\Ejemplos\Configuracion General\Configuracion_General\Configuracion_General.cydsn\Export\ARM_GCC_Generic\CapSense_P4_v7_10">
        <Files Root="D:\Documentos\UD\2023-3\Proyecto de grado\Ejemplos\Configuracion General\Configuracion_General\Configuracion_General.cydsn">
          <File BuildType="BUILD" Toolchain="ARM GCC Generic">.\Export\ARM_GCC_Generic\CapSense_P4_v7_10\Capsense_P4Library_GCCp.a</File>
        </Files>
      </Folder>
      <Folder BuildType="STRICT" Path="D:\Documentos\UD\2023-3\Proyecto de grado\Ejemplos\Configuracion General\Configuracion_General\Configuracion_General.cydsn\Export\ARM_MDK_Generic\CapSense_P4_v7_10">
        <Files Root="D:\Documentos\UD\2023-3\Proyecto de grado\Ejemplos\Configuracion General\Configuracion_General\Configuracion_General.cydsn">
          <File BuildType="BUILD" Toolchain="ARM MDK Generic">.\Export\ARM_MDK_Generic\CapSense_P4_v7_10\Capsense_P4Library_MDKp.a</File>
        </Files>
      </Folder>
      <Folder BuildType="STRICT" Path="D:\Documentos\UD\2023-3\Proyecto de grado\Ejemplos\Configuracion General\Configuracion_General\Configuracion_General.cydsn\Export\ARM_IAR_Generic\CapSense_P4_v7_10">
        <Files Root="D:\Documentos\UD\2023-3\Proyecto de grado\Ejemplos\Configuracion General\Configuracion_General\Configuracion_General.cydsn">
          <File BuildType="BUILD" Toolchain="ARM IAR Generic">.\Export\ARM_IAR_Generic\CapSense_P4_v7_10\Capsense_P4Library_IARp.a</File>
        </Files>
      </Folder>
      <Folder BuildType="EXCLUDE" Path=".\codegentemp">
        <Files Root="D:\Documentos\UD\2023-3\Proyecto de grado\Ejemplos\Configuracion General\Configuracion_General\Configuracion_General.cydsn" />
      </Folder>
      <Folder BuildType="EXCLUDE" Path=".\ARM_GCC_441">
        <Files Root="D:\Documentos\UD\2023-3\Proyecto de grado\Ejemplos\Configuracion General\Configuracion_General\Configuracion_General.cydsn" />
      </Folder>
      <Folder BuildType="EXCLUDE" Path=".\ARM_GCC_473">
        <Files Root="D:\Documentos\UD\2023-3\Proyecto de grado\Ejemplos\Configuracion General\Configuracion_General\Configuracion_General.cydsn" />
      </Folder>
      <Folder BuildType="EXCLUDE" Path=".\DP8051_Keil_952">
        <Files Root="D:\Documentos\UD\2023-3\Proyecto de grado\Ejemplos\Configuracion General\Configuracion_General\Configuracion_General.cydsn" />
      </Folder>
      <Folder BuildType="EXCLUDE" Path=".\DP8051">
        <Files Root="D:\Documentos\UD\2023-3\Proyecto de grado\Ejemplos\Configuracion General\Configuracion_General\Configuracion_General.cydsn" />
      </Folder>
      <Folder BuildType="EXCLUDE" Path=".\CortexM0">
        <Files Root="D:\Documentos\UD\2023-3\Proyecto de grado\Ejemplos\Configuracion General\Configuracion_General\Configuracion_General.cydsn" />
      </Folder>
      <Folder BuildType="EXCLUDE" Path=".\CortexM0p">
        <Files Root="D:\Documentos\UD\2023-3\Proyecto de grado\Ejemplos\Configuracion General\Configuracion_General\Configuracion_General.cydsn" />
      </Folder>
      <Folder BuildType="EXCLUDE" Path=".\CortexM3">
        <Files Root="D:\Documentos\UD\2023-3\Proyecto de grado\Ejemplos\Configuracion General\Configuracion_General\Configuracion_General.cydsn" />
      </Folder>
      <Folder BuildType="EXCLUDE" Path=".\CortexM4">
        <Files Root="D:\Documentos\UD\2023-3\Proyecto de grado\Ejemplos\Configuracion General\Configuracion_General\Configuracion_General.cydsn" />
      </Folder>
      <Folder BuildType="EXCLUDE" Path=".\CortexM7">
        <Files Root="D:\Documentos\UD\2023-3\Proyecto de grado\Ejemplos\Configuracion General\Configuracion_General\Configuracion_General.cydsn" />
      </Folder>
    </Folders>
  </Project>
</PSoCCreatorIdeExport>